meshagent/computers/__init__.py
meshagent/computers/agent.py
meshagent/computers/base_playwright.py
meshagent/computers/browserbase.py
meshagent/computers/computer.py
meshagent/computers/container_playwright.py
meshagent/computers/docker.py
meshagent/computers/local_playwright.py
meshagent/computers/operator.py
meshagent/computers/utils.py
meshagent/computers/version.py
meshagent_computers-0.25.1.dist-info/licenses/LICENSE
meshagent_computers-0.25.1.dist-info/METADATA
meshagent_computers-0.25.1.dist-info/WHEEL
meshagent_computers-0.25.1.dist-info/top_level.txt
meshagent_computers-0.25.1.dist-info/RECORD
