Metadata-Version: 2.4
Name: meshagent-computers
Version: 0.25.1
Summary: Computer Building Blocks for Meshagent
License-Expression: Apache-2.0
Project-URL: Documentation, https://docs.meshagent.com
Project-URL: Website, https://www.meshagent.com
Project-URL: Source, https://www.meshagent.com
Requires-Python: >=3.13
License-File: LICENSE
Requires-Dist: pytest~=8.4
Requires-Dist: pytest-asyncio~=0.26
Requires-Dist: openai~=2.14.0
Requires-Dist: meshagent-api~=0.25.1
Requires-Dist: meshagent-agents~=0.25.1
Requires-Dist: meshagent-tools~=0.25.1
Requires-Dist: playwright~=1.51
Requires-Dist: browserbase~=1.2
Requires-Dist: pillow~=11.3.0
Requires-Dist: python-dotenv~=1.1.1
Dynamic: license-file
